google_domains/__init__.py
google_domains/api.py
google_domains/command_line.py
google_domains/command_line_tests.py
google_domains/config.py
google_domains/config_tests.py
google_domains/log.py
google_domains/log_tests.py
google_domains/utils.py
google_domains/utils_tests.py
google_domains-0.1.9.dist-info/METADATA
google_domains-0.1.9.dist-info/WHEEL
google_domains-0.1.9.dist-info/entry_points.txt
google_domains-0.1.9.dist-info/top_level.txt
google_domains-0.1.9.dist-info/RECORD
