Metadata-Version: 2.1
Name: google-domains
Version: 0.1.9
Summary: Command-line client for Google Domains
Home-page: https://github.com/obradovic/google-domains
Author: Zo Obradovic
Author-email: ping@obradovic.com
License: UNKNOWN
Keywords: google domains
Platform: UNKNOWN
Classifier: Programming Language :: Python :: 3
Classifier: License :: OSI Approved :: MIT License
Classifier: Operating System :: OS Independent
Requires-Python: >3.6.0
Requires-Dist: python-box (>=5.0.0)
Requires-Dist: PyYAML
Requires-Dist: fqdn (>=1.2.0)
Requires-Dist: splinter (>=0.14.0)
Requires-Dist: tabulate (>=0.4.2)
